[
  { "source": "g7", "target": "g8", "type": "activation" },
  { "source": "g6", "target": "g8", "type": "activation" },
  { "source": "g8", "target": "g8", "type": "activation" },
  { "source": "g9", "target": "g1", "type": "repression" },
  { "source": "g1", "target": "g2", "type": "activation" },
  { "source": "g9", "target": "g10", "type": "activation" },
  { "source": "g5", "target": "g7", "type": "activation" },
  { "source": "g3", "target": "g5", "type": "activation" },
  { "source": "g5", "target": "g5", "type": "activation" },
  { "source": "g4", "target": "g5", "type": "repression" },
  { "source": "g8", "target": "g5", "type": "repression" },
  { "source": "g8", "target": "g9", "type": "activation" },
  { "source": "g3", "target": "g4", "type": "activation" },
  { "source": "g4", "target": "g4", "type": "activation" },
  { "source": "g5", "target": "g4", "type": "repression" },
  { "source": "g8", "target": "g4", "type": "repression" },
  { "source": "g4", "target": "g6", "type": "activation" },
  { "source": "g2", "target": "g3", "type": "activation" }
]
